sphinx-docxbuilder/__init__.py
sphinx-docxbuilder/builder.py
sphinx-docxbuilder/highlight.py
sphinx-docxbuilder/writer.py
sphinx-docxbuilder/contrib/__init__.py
sphinx-docxbuilder/contrib/exportDocx.py
sphinx-docxbuilder/contrib/quickstart.py
sphinx-docxbuilder/contrib/restructDocx.py
sphinx-docxbuilder/docx/__init__.py
sphinx-docxbuilder/docx/docx.py
sphinx_docxbuilder/__init__.py
sphinx_docxbuilder/builder.py
sphinx_docxbuilder/highlight.py
sphinx_docxbuilder/writer.py
sphinx_docxbuilder/contrib/__init__.py
sphinx_docxbuilder/contrib/exportDocx.py
sphinx_docxbuilder/contrib/quickstart.py
sphinx_docxbuilder/contrib/restructDocx.py
sphinx_docxbuilder/docx/__init__.py
sphinx_docxbuilder/docx/docx.py
sphinx_docxbuilder-2019.1.28.post1.dist-info/DESCRIPTION.rst
sphinx_docxbuilder-2019.1.28.post1.dist-info/METADATA
sphinx_docxbuilder-2019.1.28.post1.dist-info/RECORD
sphinx_docxbuilder-2019.1.28.post1.dist-info/WHEEL
sphinx_docxbuilder-2019.1.28.post1.dist-info/metadata.json
sphinx_docxbuilder-2019.1.28.post1.dist-info/top_level.txt
