Metadata-Version: 2.0
Name: sphinx-docxbuilder
Version: 2019.1.28.post1
Summary: An extension for a docx file generation with Sphinx (Fork of https://bitbucket.org/haraisao/sphinx-docxbuilder)
Home-page: https://github.com/Lightslayer/sphinx-docxbuilder
Author: Isao Hara
Author-email: isao-hara@aist.go.jp
Maintainer: Liam Deacon
Maintainer-email: liam.m.deacon@gmail.com
License: MIT License
Platform: UNKNOWN
Classifier: Programming Language :: Python
Classifier: Framework :: Sphinx :: Extension
Classifier: Topic :: Documentation :: Sphinx
Requires-Python: >=2.7
Requires-Dist: lxml
Requires-Dist: pillow
